document_verifier_Silent_Canary/__init__.py
document_verifier_Silent_Canary/face_match.py
document_verifier_Silent_Canary/ocr_text.py
document_verifier_Silent_Canary/qr.py
document_verifier_Silent_Canary/utils.py
document_verifier_Silent_Canary/verifier.py
civic_verifier-0.1.0.dist-info/METADATA
civic_verifier-0.1.0.dist-info/WHEEL
civic_verifier-0.1.0.dist-info/top_level.txt
civic_verifier-0.1.0.dist-info/RECORD
