Metadata-Version: 2.4
Name: civic_verifier
Version: 0.1.0
Summary: Document verification package
Author: Advitiya Prakash
Author-email: advitiyaprakash08@gmail.com
Requires-Python: >=3.6
Dynamic: author
Dynamic: author-email
Dynamic: requires-python
Dynamic: summary
